yougotmapped/__init__.py
yougotmapped/cli.py
yougotmapped/utils/__init__.py
yougotmapped/utils/anonymity.py
yougotmapped/utils/dependencies.py
yougotmapped/utils/mapping.py
yougotmapped/utils/network.py
yougotmapped/utils/output.py
yougotmapped/utils/ping.py
yougotmapped/utils/token.py
yougotmapped/utils/trace.py
yougotmapped-1.0.2.dist-info/licenses/LICENSE
yougotmapped-1.0.2.dist-info/METADATA
yougotmapped-1.0.2.dist-info/WHEEL
yougotmapped-1.0.2.dist-info/entry_points.txt
yougotmapped-1.0.2.dist-info/top_level.txt
yougotmapped-1.0.2.dist-info/RECORD
