Metadata-Version: 2.4
Name: yougotmapped
Version: 1.0.2
Summary: A terminal tool to map IPs and domains with style.
Home-page: https://github.com/diputs-sudo/YouGotMapped
Author: diputs
Author-email: diputs-sudo@proton.me
License: MIT
Classifier: Programming Language :: Python :: 3
Classifier: License :: OSI Approved :: MIT License
Classifier: Operating System :: OS Independent
Requires-Python: >=3.7
License-File: LICENSE
Requires-Dist: requests
Requires-Dist: folium
Requires-Dist: python-dotenv
Requires-Dist: ping3
Dynamic: author
Dynamic: author-email
Dynamic: classifier
Dynamic: description
Dynamic: description-content-type
Dynamic: home-page
Dynamic: license
Dynamic: license-file
Dynamic: requires-dist
Dynamic: requires-python
Dynamic: summary
